usbmuxwrapper/__init__.py
usbmuxwrapper-0.0.3.dist-info/LICENSE
usbmuxwrapper-0.0.3.dist-info/METADATA
usbmuxwrapper-0.0.3.dist-info/WHEEL
usbmuxwrapper-0.0.3.dist-info/top_level.txt
usbmuxwrapper-0.0.3.dist-info/RECORD
